tests/__init__.py
tests/test_builder.py
uribuilder/__init__.py
uribuilder/builder.py
uribuilder-0.1a1.dist-info/METADATA
uribuilder-0.1a1.dist-info/RECORD
uribuilder-0.1a1.dist-info/WHEEL
uribuilder-0.1a1.dist-info/top_level.txt
