Metadata-Version: 2.1
Name: uribuilder
Version: 0.1a1
Summary: Build URI.
Home-page: https://github.com/dexpota/uribuilder
Author: Fabrizio Destro
Author-email: destro.fabrizio@gmail.com
License: UNKNOWN
Platform: UNKNOWN
Classifier: Development Status :: 3 - Alpha
Classifier: Intended Audience :: Developers
Classifier: Programming Language :: Python :: 3
